{
  "cards": [
    {
      "id": "72388432b1e6",
      "term": "Haas #2",
      "definition": "Esteban Ocon – Experienced hired hand meant to stabilize the garage; mentors points-scoring Saturdays while Bearman absorbs the ruthless mileage.",
      "next_review": "2026-05-16",
      "ease_factor": 2.45,
      "interval": 2,
      "difficulty": 0,
      "completed_today": true,
      "first_rating": null,
      "session_attempts": 0,
      "consecutive_easy_sessions": 0,
      "latest_rating": null
    },
    {
      "id": "3ecb801f53c1",
      "term": "Williams #1",
      "definition": "Alexander Albon – Williams’ cornerstone through the rebuild; keeps the team humane on tough weekends while absorbing another strong teammate pairing.",
      "next_review": "2026-05-15",
      "ease_factor": 2.3500000000000005,
      "interval": 1,
      "difficulty": 0,
      "completed_today": true,
      "first_rating": null,
      "session_attempts": 0,
      "consecutive_easy_sessions": 0,
      "latest_rating": null
    },
    {
      "id": "9f4349d90e10",
      "term": "McLaren #2",
      "definition": "Oscar Piastri – Came within a whisker of denying Norris 2025; same machinery again so every quali duel is championship infrastructure, not melodrama.",
      "next_review": "2026-05-16",
      "ease_factor": 2.35,
      "interval": 2,
      "difficulty": 1,
      "completed_today": true,
      "first_rating": null,
      "session_attempts": 0,
      "consecutive_easy_sessions": 0,
      "latest_rating": null
    },
    {
      "id": "5c316df6b882",
      "term": "Haas #1",
      "definition": "Oliver Bearman – Ferrari-backed full-time rookie after heroic stand-ins; Haas Ferrari power makes him both development bridge and spotlight kid.",
      "next_review": "2026-05-16",
      "ease_factor": 2.35,
      "interval": 2,
      "difficulty": 1,
      "completed_today": true,
      "first_rating": null,
      "session_attempts": 0,
      "consecutive_easy_sessions": 0,
      "latest_rating": null
    },
    {
      "id": "b6c46c34d5d6",
      "term": "Ferrari #2",
      "definition": "Lewis Hamilton – The blockbuster move from Mercedes—chasing titles in red is the headline of the season and reframes every Ferrari strategy call.",
      "next_review": "2026-05-16",
      "ease_factor": 2.45,
      "interval": 2,
      "difficulty": 0,
      "completed_today": true,
      "first_rating": null,
      "session_attempts": 0,
      "consecutive_easy_sessions": 0,
      "latest_rating": null
    },
    {
      "id": "057786e4a436",
      "term": "Mercedes #2",
      "definition": "George Russell – Becomes undisputed senior in Brackley; Mercedes’ rebound narrative sits on his shoulders while he schools F1’s most hyped debut.",
      "next_review": "2026-05-15",
      "ease_factor": 1.9500000000000002,
      "interval": 1,
      "difficulty": 4,
      "completed_today": true,
      "first_rating": null,
      "session_attempts": 0,
      "consecutive_easy_sessions": 0,
      "latest_rating": null
    },
    {
      "id": "2f7d3f6b5609",
      "term": "McLaren #1",
      "definition": "Lando Norris – Reigning champion running #1—first McLaren crown in generations means 2026 is defense mode with the factory and Piastri both hunting him.",
      "next_review": "2026-05-15",
      "ease_factor": 2.2500000000000004,
      "interval": 1,
      "difficulty": 1,
      "completed_today": true,
      "first_rating": null,
      "session_attempts": 0,
      "consecutive_easy_sessions": 0,
      "latest_rating": null
    },
    {
      "id": "dd3ed1c7dcbb",
      "term": "Audi #2",
      "definition": "Gabriel Bortoleto – Brazilian rookie fresh from junior titles; Audi’s upside bet—young speed paired with Hülkenberg’s setup discipline.",
      "next_review": "2026-05-17",
      "ease_factor": 2.5,
      "interval": 3,
      "difficulty": 0,
      "completed_today": true,
      "first_rating": null,
      "session_attempts": 0,
      "consecutive_easy_sessions": 1,
      "latest_rating": null
    },
    {
      "id": "b0d95fa869fd",
      "term": "Aston Martin #2",
      "definition": "Lance Stroll – Continuity seat under Lawrence Stroll’s project; the story is unchanged: measured against Alonso’s weekends, not midfield peers.",
      "next_review": "2026-05-16",
      "ease_factor": 2.3000000000000003,
      "interval": 2,
      "difficulty": 1,
      "completed_today": true,
      "first_rating": null,
      "session_attempts": 0,
      "consecutive_easy_sessions": 0,
      "latest_rating": null
    },
    {
      "id": "bf4d6dd51aca",
      "term": "Cadillac #1",
      "definition": "Valtteri Bottas – Dealer’s-choice veteran for GM/Cadillac’s debut; counted on for clean feedback and points on day one while F1 validates a true eleventh constructor.",
      "next_review": "2026-05-15",
      "ease_factor": 1.85,
      "interval": 1,
      "difficulty": 5,
      "completed_today": true,
      "first_rating": null,
      "session_attempts": 0,
      "consecutive_easy_sessions": 0,
      "latest_rating": null
    },
    {
      "id": "220fa1c2b09e",
      "term": "Williams #2",
      "definition": "Carlos Sainz – Winner pedigreed into Grove to drag Williams toward regular Q3—not a leisurely career phase but a reputational rebound mission.",
      "next_review": "2026-05-16",
      "ease_factor": 2.45,
      "interval": 2,
      "difficulty": 0,
      "completed_today": true,
      "first_rating": null,
      "session_attempts": 0,
      "consecutive_easy_sessions": 0,
      "latest_rating": null
    },
    {
      "id": "437301aa0889",
      "term": "Aston Martin #1",
      "definition": "Fernando Alonso – Honda power from 2026; at his age every season is “how long can he stay at the sharp end”—still Aston’s ruthless reference lap.",
      "next_review": "2026-05-17",
      "ease_factor": 2.5,
      "interval": 3,
      "difficulty": 0,
      "completed_today": true,
      "first_rating": null,
      "session_attempts": 0,
      "consecutive_easy_sessions": 1,
      "latest_rating": null
    },
    {
      "id": "904cb192e10a",
      "term": "Ferrari #1",
      "definition": "Charles Leclerc – Maranello native lead as the scarlet cars enter 2026’s big aero/power reset; internally he’s the incumbent whose yardstick is suddenly an all-time champion teammate.",
      "next_review": "2026-05-16",
      "ease_factor": 2.45,
      "interval": 2,
      "difficulty": 0,
      "completed_today": true,
      "first_rating": null,
      "session_attempts": 0,
      "consecutive_easy_sessions": 0,
      "latest_rating": null
    },
    {
      "id": "dd4a2203909b",
      "term": "Racing Bulls #2",
      "definition": "Arvid Lindblad – Teenage Red Bull-backed debut stacked next to Lawson; textbook “earn your superlicence, then catch the car” season with zero grace period.",
      "next_review": "2026-05-15",
      "ease_factor": 2.2500000000000004,
      "interval": 1,
      "difficulty": 1,
      "completed_today": true,
      "first_rating": null,
      "session_attempts": 0,
      "consecutive_easy_sessions": 0,
      "latest_rating": null
    },
    {
      "id": "d02c3d37ffab",
      "term": "Alpine #2",
      "definition": "Franco Colapinto – Year two after a chaotic rookie splash; expectations shift from survival to repeatable points with Gasly as the intra-team ruler.",
      "next_review": "2026-05-30",
      "ease_factor": 2.5,
      "interval": 16,
      "difficulty": 0,
      "completed_today": true,
      "first_rating": null,
      "session_attempts": 0,
      "consecutive_easy_sessions": 2,
      "latest_rating": null
    },
    {
      "id": "341011e75cfb",
      "term": "Cadillac #2",
      "definition": "Sergio Perez – Sixth seat for Checo narrative is over—now he must author Cadillac’s maiden season alongside Bottas while Ferrari hardware answers reliability questions first.",
      "next_review": "2026-05-16",
      "ease_factor": 2.45,
      "interval": 2,
      "difficulty": 0,
      "completed_today": true,
      "first_rating": null,
      "session_attempts": 0,
      "consecutive_easy_sessions": 0,
      "latest_rating": null
    },
    {
      "id": "5d9809f4f6bf",
      "term": "Racing Bulls #1",
      "definition": "Liam Lawson – Second Red Bull stable chance after turbulence; Visa RB/Lawson timelines reset—produce now or juniors queue behind him.",
      "next_review": "2026-05-16",
      "ease_factor": 2.45,
      "interval": 2,
      "difficulty": 0,
      "completed_today": true,
      "first_rating": null,
      "session_attempts": 0,
      "consecutive_easy_sessions": 0,
      "latest_rating": null
    },
    {
      "id": "cb06a1dafcbb",
      "term": "Red Bull #1",
      "definition": "Max Verstappen – Still the reference driver; 2026 rules reset is the first real chance the field erodes his advantage—every upgrade story is about catching him.",
      "next_review": "2026-05-15",
      "ease_factor": 2.2500000000000004,
      "interval": 1,
      "difficulty": 1,
      "completed_today": true,
      "first_rating": null,
      "session_attempts": 0,
      "consecutive_easy_sessions": 0,
      "latest_rating": null
    },
    {
      "id": "672d6a36b134",
      "term": "Alpine #1",
      "definition": "Pierre Gasly – Lone French cornerstone at Enstone; 2026 is about dragging Alpine up the grid with Mercedes power while the team rebrands mentally around him.",
      "next_review": "2026-05-16",
      "ease_factor": 2.35,
      "interval": 2,
      "difficulty": 1,
      "completed_today": true,
      "first_rating": null,
      "session_attempts": 0,
      "consecutive_easy_sessions": 0,
      "latest_rating": null
    },
    {
      "id": "24707ad02392",
      "term": "Audi #1",
      "definition": "Nico Hülkenberg – The German “reset button” figure as Sauber races under Audi’s works identity; tasked with punching above the car early in a long works climb.",
      "next_review": "2026-05-15",
      "ease_factor": 2.3500000000000005,
      "interval": 1,
      "difficulty": 0,
      "completed_today": true,
      "first_rating": null,
      "session_attempts": 0,
      "consecutive_easy_sessions": 0,
      "latest_rating": null
    },
    {
      "id": "697c6f92a9ff",
      "term": "Mercedes #1",
      "definition": "Kimi Antonelli – Fast-tracked rookie replacing Hamilton lore; skips the usual ladders and carries Toto-era pressure to prove Mercedes didn’t gamble the seat.",
      "next_review": "2026-05-15",
      "ease_factor": 1.85,
      "interval": 1,
      "difficulty": 5,
      "completed_today": true,
      "first_rating": null,
      "session_attempts": 0,
      "consecutive_easy_sessions": 0,
      "latest_rating": null
    },
    {
      "id": "65c1bd1b234b",
      "term": "Red Bull #2",
      "definition": "Isack Hadjar – Promoted to partner Verstappen as Tsunoda steps aside; sinks-or-swims beside the benchmark while Red Bull’s junior politics watch every error.",
      "next_review": "2026-05-30",
      "ease_factor": 2.5,
      "interval": 16,
      "difficulty": 0,
      "completed_today": true,
      "first_rating": null,
      "session_attempts": 0,
      "consecutive_easy_sessions": 2,
      "latest_rating": null
    }
  ],
  "last_session_date": "2026-05-17"
}